galaxy/client/__init__.py
galaxy/client/install.py
galaxy/client/dist/00950d3d0eabc9b79c13.png
galaxy/client/dist/00b14a051b8ec5846ca4.png
galaxy/client/dist/015bb398cc86c8e2c532.png
galaxy/client/dist/0a09dd8bcca1e540a97f.png
galaxy/client/dist/0c708255f16de429468f.png
galaxy/client/dist/1444303e4f0c0f62fa36.png
galaxy/client/dist/1551f4f60c37af51121f.woff2
galaxy/client/dist/175327482730212e7000.png
galaxy/client/dist/17aaaa49460f37c9589a.png
galaxy/client/dist/2285773e6b4b172f07d9.woff
galaxy/client/dist/231.bundled.js
galaxy/client/dist/23f19bb08961f37aaf69.eot
galaxy/client/dist/271fbfa6f4bd5c11cea8.woff
galaxy/client/dist/27c5873e9e627196c882.png
galaxy/client/dist/2f2c06d22919cab5a524.png
galaxy/client/dist/2f517e09eb2ca6650ff5.svg
galaxy/client/dist/315.bundled.js
galaxy/client/dist/31bc77d4f6f4dbe60b99.png
galaxy/client/dist/3458c7b831d6a8909f76.png
galaxy/client/dist/354.bundled.js
galaxy/client/dist/354.bundled.js.LICENSE.txt
galaxy/client/dist/36d93ca016d18f6fc3e6.png
galaxy/client/dist/37478264c4ed6b0da2cb.png
galaxy/client/dist/3fa7cde9c3400ad8112a.png
galaxy/client/dist/40e48ce346be3ec51671.png
galaxy/client/dist/435.bundled.js
galaxy/client/dist/441.bundled.js
galaxy/client/dist/448.bundled.js
galaxy/client/dist/4689f52cc96215721344.svg
galaxy/client/dist/47683caf7120e987ca85.png
galaxy/client/dist/47b9475d2b6a19bc0921.png
galaxy/client/dist/491974d108fe4002b2aa.ttf
galaxy/client/dist/4f7d1754d42d174d17b3.woff
galaxy/client/dist/5000254d328af6822042.gif
galaxy/client/dist/50a457cf9caf3ff7d302.png
galaxy/client/dist/523592c8f36ba8d3d7b1.png
galaxy/client/dist/527940b104eb2ea366c8.ttf
galaxy/client/dist/564668c1dbc7c9509d9d.png
galaxy/client/dist/56d4c7ce2d3591a02107.gif
galaxy/client/dist/596.bundled.js
galaxy/client/dist/596.bundled.js.LICENSE.txt
galaxy/client/dist/5c2e7e18ad426822d1f3.png
galaxy/client/dist/5f8db17a927f4c77d0a7.png
galaxy/client/dist/616.bundled.js
galaxy/client/dist/688bccf95583ddf2ba42.png
galaxy_client-25.0.dev0.dist-info/METADATA
galaxy_client-25.0.dev0.dist-info/WHEEL
galaxy_client-25.0.dev0.dist-info/entry_points.txt
galaxy_client-25.0.dev0.dist-info/top_level.txt
galaxy_client-25.0.dev0.dist-info/RECORD
